AUTHORS
ChangeLog
LICENSE.rst
README.rst
setup.cfg
setup.py
django_robotice_auth.egg-info/PKG-INFO
django_robotice_auth.egg-info/SOURCES.txt
django_robotice_auth.egg-info/dependency_links.txt
django_robotice_auth.egg-info/not-zip-safe
django_robotice_auth.egg-info/pbr.json
django_robotice_auth.egg-info/top_level.txt
robotice_auth/__init__.py
robotice_auth/backend.py
robotice_auth/exceptions.py
robotice_auth/forms.py
robotice_auth/requirements.txt
robotice_auth/urls.py
robotice_auth/user.py
robotice_auth/utils.py
robotice_auth/views.py